bootstrap.py
buildout.cfg
setup.py
src/keas/__init__.py
src/keas.pbpersist.egg-info/PKG-INFO
src/keas.pbpersist.egg-info/SOURCES.txt
src/keas.pbpersist.egg-info/dependency_links.txt
src/keas.pbpersist.egg-info/namespace_packages.txt
src/keas.pbpersist.egg-info/requires.txt
src/keas.pbpersist.egg-info/top_level.txt
src/keas/pbpersist/README.txt
src/keas/pbpersist/__init__.py
src/keas/pbpersist/pbformat.py
src/keas/pbpersist/persistent.proto
src/keas/pbpersist/persistent_pb2.py
src/keas/pbpersist/tests.py