Metadata-Version: 1.0
Name: keas.pbpersist
Version: 0.1
Summary: ZODB Persistence in a Google Protocol Buffer
Home-page: UNKNOWN
Author: Shane Hathaway and the Zope Community
Author-email: zope-dev@zope.org
License: ZPL 2.1
Platform: UNKNOWN
